rainrain/__init__.py
rainrain/weather.py
rainrain-0.2.0.dist-info/LICENSE.txt
rainrain-0.2.0.dist-info/METADATA
rainrain-0.2.0.dist-info/WHEEL
rainrain-0.2.0.dist-info/top_level.txt
rainrain-0.2.0.dist-info/RECORD
