Metadata-Version: 2.1
Name: rainrain
Version: 0.2.0
Summary: weather app
Author-email: prajil <prajiltpriyan@gmail.com>
Classifier: Programming Language :: Python :: 3
Classifier: License :: OSI Approved :: MIT License
Classifier: Operating System :: OS Independent
Requires-Python: >=3.7
License-File: LICENSE.txt
